openfeature/contrib/provider/ofrep/__init__.py
openfeature_provider_ofrep-0.2.0.dist-info/WHEEL
openfeature_provider_ofrep-0.2.0.dist-info/entry_points.txt
openfeature_provider_ofrep-0.2.0.dist-info/METADATA
openfeature_provider_ofrep-0.2.0.dist-info/RECORD
