Metadata-Version: 2.3
Name: openfeature-provider-ofrep
Version: 0.2.0
Summary: OpenFeature provider for the OpenFeature Remote Evaluation Protocol (OFREP)
Keywords: 
Author: OpenFeature
Author-email: OpenFeature <openfeature-core@groups.io>
License:                                  Apache License
Classifier: License :: OSI Approved :: Apache Software License
Classifier: Programming Language :: Python
Classifier: Programming Language :: Python :: 3
Requires-Dist: openfeature-sdk>=0.8.2
Requires-Dist: requests>=2.27.0
Requires-Python: >=3.9
Project-URL: Homepage, https://github.com/open-feature/python-sdk-contrib
